README.md
setup.py
pyrir/__init__.py
pyrir/microphone.py
pyrir/room.py
pyrir/speaker.py
pyrir.egg-info/PKG-INFO
pyrir.egg-info/SOURCES.txt
pyrir.egg-info/dependency_links.txt
pyrir.egg-info/top_level.txt
pyrir/cyrir/__init__.py
pyrir/cyrir/cyrir.c
pyrir/cyrir/cyrir.pyx
pyrir/cyrir/rir.c