Metadata-Version: 2.1
Name: pyrir
Version: 0.0.1
Summary: Lite Package for Room Impulse Response
Home-page: https://github.com/ludlows/pyrir
Author: ludlows
License: UNKNOWN
Platform: UNKNOWN
Classifier: Programming Language :: Python
Classifier: License :: OSI Approved :: MIT License
Classifier: Operating System :: OS Independent
